cookiecutter_maker/__init__.py
cookiecutter_maker/_version.py
cookiecutter_maker/api.py
cookiecutter_maker/docs/__init__.py
cookiecutter_maker/exc.py
cookiecutter_maker/maker.py
cookiecutter_maker/parameter.py
cookiecutter_maker/path_matcher.py
cookiecutter_maker/paths.py
cookiecutter_maker/str_replace.py
cookiecutter_maker/tests/__init__.py
cookiecutter_maker/tests/case.py
cookiecutter_maker/tests/helper.py
cookiecutter_maker/vendor/__init__.py
cookiecutter_maker/vendor/better_pathlib.py
cookiecutter_maker/vendor/pytest_cov_helper.py
cookiecutter_maker-1.0.2.dist-info/AUTHORS.rst
cookiecutter_maker-1.0.2.dist-info/LICENSE.txt
cookiecutter_maker-1.0.2.dist-info/METADATA
cookiecutter_maker-1.0.2.dist-info/WHEEL
cookiecutter_maker-1.0.2.dist-info/RECORD
